pysnver/__init__.py
pysnver/sn.py
pysnver/so/libcim.so
pysnver/so/libsv.so
pysnver-0.2.21.dist-info/METADATA
pysnver-0.2.21.dist-info/WHEEL
pysnver-0.2.21.dist-info/top_level.txt
pysnver-0.2.21.dist-info/RECORD
