Metadata-Version: 2.1
Name: pysnver
Version: 0.2.21
Summary: python sn verify
Home-page: UNKNOWN
License: UNKNOWN
Platform: UNKNOWN
Classifier: Programming Language :: Python :: 3
